peepdf/JSAnalysis.py
peepdf/PDFConsole.py
peepdf/PDFCore.py
peepdf/PDFCrypto.py
peepdf/PDFEnDec.py
peepdf/PDFFilters.py
peepdf/PDFUtils.py
peepdf/PDFVulns.py
peepdf/__init__.py
peepdf/__main__.py
peepdf/peepdf.py
peepdf_3-5.1.1.dist-info/licenses/COPYING
peepdf_3-5.1.1.dist-info/METADATA
peepdf_3-5.1.1.dist-info/WHEEL
peepdf_3-5.1.1.dist-info/entry_points.txt
peepdf_3-5.1.1.dist-info/top_level.txt
peepdf_3-5.1.1.dist-info/RECORD
