Metadata-Version: 2.4
Name: peepdf-3
Version: 5.1.1
Summary: A Python 3 tool to explore, analyse, and disassemble PDF files
Author: Jose Miguel Esparza
Author-email: "Corey Forman (digitalsleuth)" <github@digitalsleuth.ca>
Maintainer-email: "Corey Forman (digitalsleuth)" <github@digitalsleuth.ca>
Project-URL: Homepage, https://github.com/digitalsleuth/peepdf-3
Project-URL: Changelog, https://github.com/digitalsleuth/peepdf-3/blob/main/CHANGELOG.md
Project-URL: Wiki, https://github.com/digitalsleuth/peepdf-3/wiki
Keywords: pdf,peepdf,forensics
Classifier: Development Status :: 5 - Production/Stable
Classifier: Programming Language :: Python :: 3
Requires-Python: >=3.9
License-File: COPYING
Requires-Dist: requests
Requires-Dist: pypdf
Requires-Dist: jsbeautifier
Requires-Dist: colorama
Requires-Dist: Pillow
Requires-Dist: pythonaes
Requires-Dist: lxml
Requires-Dist: prettytable>=3.12.0
Requires-Dist: STPyV8
Dynamic: license-file
